{"ed1fdf99d1244a741636040b4901c19e:5bd835b0d6b1d4ada3b9f0db936e82c8":{"statistic":{"failed":0,"broken":0,"skipped":0,"passed":1,"unknown":0,"total":1},"items":[{"uid":"a3c90cbe021b266d","reportUrl":"https://hngocanh.github.io/playwright-project-allure/7//#testresult/a3c90cbe021b266d","status":"passed","time":{"start":1693043063515,"stop":1693043066480,"duration":2965}}]},"c2b98918ad561c7c443e7c60fa840266:5bd835b0d6b1d4ada3b9f0db936e82c8":{"statistic":{"failed":0,"broken":0,"skipped":0,"passed":1,"unknown":0,"total":1},"items":[{"uid":"2f28ca0f28d5eb58","reportUrl":"https://hngocanh.github.io/playwright-project-allure/7//#testresult/2f28ca0f28d5eb58","status":"passed","time":{"start":1693043059111,"stop":1693043063511,"duration":4400}}]},"4ce3cc3c04c17b1e89c037fd785a69ba:5bd835b0d6b1d4ada3b9f0db936e82c8":{"statistic":{"failed":0,"broken":0,"skipped":0,"passed":1,"unknown":0,"total":1},"items":[{"uid":"d76634a9da0257b8","reportUrl":"https://hngocanh.github.io/playwright-project-allure/7//#testresult/d76634a9da0257b8","status":"passed","time":{"start":1693043066481,"stop":1693043070265,"duration":3784}}]}}